parsekit/__init__.py
parsekit/combinators.py
parsekit/primitives.py
parsekit/typing.py
parsekit/utils.py
python_parsekit-1.2.2.dist-info/LICENSE
python_parsekit-1.2.2.dist-info/METADATA
python_parsekit-1.2.2.dist-info/WHEEL
python_parsekit-1.2.2.dist-info/top_level.txt
python_parsekit-1.2.2.dist-info/RECORD
